pydb3/__init__.py
pydb3/db.py
pydb3/adapter/__init__.py
pydb3/adapter/mysql.py
pydb3/adapter/sqlite.py
pydb3/config/__init__.py
pydb3/config/property.py
pydb3/config/weight.py
pydb3/log/__init__.py
pydb3/log/log.py
pydb3/model/__init__.py
pydb3/model/blob.py
pydb3/model/char.py
pydb3/model/date.py
pydb3/model/datetime.py
pydb3/model/double.py
pydb3/model/float.py
pydb3/model/image.py
pydb3/model/int.py
pydb3/model/integer.py
pydb3/model/model.py
pydb3/model/text.py
pydb3/model/varchar.py
pydb3/sql/__init__.py
pydb3/sql/generator/__init__.py
pydb3/sql/generator/delete.py
pydb3/sql/generator/insert.py
pydb3/sql/generator/public.py
pydb3/sql/generator/select.py
pydb3/sql/generator/table.py
pydb3/sql/generator/update.py
pydb3/utils/__init__.py
pydb3/utils/request.py
pydb3/utils/valid.py
pydb3-0.0.7.dist-info/LICENSE.txt
pydb3-0.0.7.dist-info/METADATA
pydb3-0.0.7.dist-info/WHEEL
pydb3-0.0.7.dist-info/top_level.txt
pydb3-0.0.7.dist-info/RECORD
