Metadata-Version: 2.1
Name: pydb3
Version: 0.0.7
Summary: connect to database
Home-page: https://gitee.com/gan_jianwen/db-library
Author: 甘建文
Author-email: 1727949032@qq.com
License: UNKNOWN
Platform: UNKNOWN
Classifier: Programming Language :: Python :: 3
Classifier: License :: OSI Approved :: MIT License
Classifier: Operating System :: OS Independent
Requires-Python: >=3.6
License-File: LICENSE.txt
Requires-Dist: pymongo
Requires-Dist: pymysql
Requires-Dist: requests
Requires-Dist: openpyxl
